unittest_prettify/__init__.py
unittest_prettify/colorize.py
unittest_prettify-1.0.post4.dist-info/LICENSE.txt
unittest_prettify-1.0.post4.dist-info/METADATA
unittest_prettify-1.0.post4.dist-info/WHEEL
unittest_prettify-1.0.post4.dist-info/top_level.txt
unittest_prettify-1.0.post4.dist-info/RECORD
