Metadata-Version: 2.1
Name: unittest-prettify
Version: 1.0.post4
Summary: A simple module to improve the unittest output.
Home-page: https://github.com/jonathadv/unittest-prettify/
Author: Jonatha Daguerre
Author-email: jonatha@daguerre.com.br
License: MIT
Platform: UNKNOWN
Classifier: Development Status :: 4 - Beta
Classifier: Intended Audience :: Developers
Classifier: Natural Language :: English
Classifier: License :: OSI Approved :: MIT License
Classifier: Programming Language :: Python
Classifier: Programming Language :: Python :: 3
Classifier: Programming Language :: Python :: 3.5
Classifier: Programming Language :: Python :: 3.6
Classifier: Programming Language :: Python :: Implementation :: CPython
Requires-Python: >=3.5.*
